code_ctags-0.1.5.dist-info/METADATA
code_ctags-0.1.5.dist-info/WHEEL
code_ctags-0.1.5.dist-info/entry_points.txt
code_ctags/__init__.py
code_ctags/main.py
code_ctags/repomap.py
code_ctags-0.1.5.dist-info/RECORD
